circuit.v
`timescale 1ns / 1ps
`include "iob_lib.vh"
//pleasee let this work
module circuit
  #(
    parameter W=32
    )
  (
   `INPUT(rst,1),
   `INPUT(clk,1),
   `INPUT(r,100),
   `INPUT(en,1),
   
   `OUTPUT(y,100)
   );

   `SIGNAL(cnt, 7) //7-bit counter as iterator
   `SIGNAL(acc_r, 100) //numero random
   `SIGNAL(y_int, 100) //internal y
   `SIGNAL(y_int_n_1, 100) //y(n-1) registo onde é guardado
  
   `SIGNAL2OUT(y, y_int) //connect internal y to output

   //y shift register 
   `REG_ARE(clk, rst, 1'b0, cnt!=99, y_int_n_1, y_int)


   //iteration counter
   `COUNTER_ARE(clk, rst, cnt!=99, cnt)

  //testestestes

   `COMB y_int = 2*(y_int_n_1) + acc_r ;
   
   
endmodule

circuit_tb.v
`timescale 1ns / 1ps
`include "iob_lib.vh"

`define W 96

module circuit_tb;

   `CLOCK(clk, 10)
   `RESET(rst, 1, 10)
   `SIGNAL(en, 1)
     `SIGNAL(r, 32)// sinal que armazena o número aleatório
  `SIGNAL(y, 32)
   `SIGNAL_OUT(y, `W)

   integer i;
   
   initial begin
      $dumpfile("circuit.vcd");
      $dumpvars();
      en=0;
      for (i=0; i<100; i=i+1) begin
         @(posedge clk) #1 r= $random%2048; en=1; $display("%d: %d",i+1,r, y) en=1;
          @(posedge clk) #1 en=0;
      end

      @(posedge clk) #100 $finish;

   end 

   circuit
     #(
       .W(`W)
       ) 
   c0
     (
      .rst(rst),
      .clk(clk),
      .en(en),
      .r(r),
      .y(y)
      );


endmodule

circuit.vcd
$date
	Tue Nov 17 22:39:01 2020
$end
$version
	Icarus Verilog
$end
$timescale
	1ps
$end
$scope module circuit_tb $end
$var wire 96 ! y [95:0] $end
$var reg 1 " clk $end
$var reg 1 # en $end
$var reg 1 $ rst $end
$var integer 32 % i [31:0] $end
$scope module c0 $end
$var wire 1 " clk $end
$var wire 1 # en $end
$var wire 100 & r [99:0] $end
$var wire 1 $ rst $end
$var wire 100 ' y [99:0] $end
$var reg 100 ( acc_r [99:0] $end
$var reg 7 ) cnt [6:0] $end
$var reg 100 * y_int [99:0] $end
$var reg 100 + y_int_n_1 [99:0] $end
$upscope $end
$upscope $end
$enddefinitions $end
#0
$dumpvars
bx +
bx *
bx )
bx (
bx '
bz &
b0 %
0$
0#
1"
bx !
$end
#1000
b0 )
b0 +
1$
#5000
0"
#10000
1"
#11000
b1 %
1#
0$
#15000
0"
#20000
b1 )
bx +
1"
#21000
b10 %
#25000
0"
#30000
b10 )
1"
#31000
b11 %
#35000
0"
#40000
b11 )
1"
#41000
b100 %
#45000
0"
#50000
b100 )
1"
#51000
b101 %
#55000
0"
#60000
b101 )
1"
#61000
b110 %
#65000
0"
#70000
b110 )
1"
#71000
b111 %
#75000
0"
#80000
b111 )
1"
#81000
b1000 %
#85000
0"
#90000
b1000 )
1"
#91000
b1001 %
#95000
0"
#100000
b1001 )
1"
#101000
b1010 %
#105000
0"
#110000
b1010 )
1"
#111000
b1011 %
#115000
0"
#120000
b1011 )
1"
#121000
b1100 %
#125000
0"
#130000
b1100 )
1"
#131000
b1101 %
#135000
0"
#140000
b1101 )
1"
#141000
b1110 %
#145000
0"
#150000
b1110 )
1"
#151000
b1111 %
#155000
0"
#160000
b1111 )
1"
#161000
b10000 %
#165000
0"
#170000
b10000 )
1"
#171000
b10001 %
#175000
0"
#180000
b10001 )
1"
#181000
b10010 %
#185000
0"
#190000
b10010 )
1"
#191000
b10011 %
#195000
0"
#200000
b10011 )
1"
#201000
b10100 %
#205000
0"
#210000
b10100 )
1"
#211000
b10101 %
#215000
0"
#220000
b10101 )
1"
#221000
b10110 %
#225000
0"
#230000
b10110 )
1"
#231000
b10111 %
#235000
0"
#240000
b10111 )
1"
#241000
b11000 %
#245000
0"
#250000
b11000 )
1"
#251000
b11001 %
#255000
0"
#260000
b11001 )
1"
#261000
b11010 %
#265000
0"
#270000
b11010 )
1"
#271000
b11011 %
#275000
0"
#280000
b11011 )
1"
#281000
b11100 %
#285000
0"
#290000
b11100 )
1"
#291000
b11101 %
#295000
0"
#300000
b11101 )
1"
#301000
b11110 %
#305000
0"
#310000
b11110 )
1"
#311000
b11111 %
#315000
0"
#320000
b11111 )
1"
#321000
b100000 %
#325000
0"
#330000
b100000 )
1"
#331000
b100001 %
#335000
0"
#340000
b100001 )
1"
#341000
b100010 %
#345000
0"
#350000
b100010 )
1"
#351000
b100011 %
#355000
0"
#360000
b100011 )
1"
#361000
b100100 %
#365000
0"
#370000
b100100 )
1"
#371000
b100101 %
#375000
0"
#380000
b100101 )
1"
#381000
b100110 %
#385000
0"
#390000
b100110 )
1"
#391000
b100111 %
#395000
0"
#400000
b100111 )
1"
#401000
b101000 %
#405000
0"
#410000
b101000 )
1"
#411000
b101001 %
#415000
0"
#420000
b101001 )
1"
#421000
b101010 %
#425000
0"
#430000
b101010 )
1"
#431000
b101011 %
#435000
0"
#440000
b101011 )
1"
#441000
b101100 %
#445000
0"
#450000
b101100 )
1"
#451000
b101101 %
#455000
0"
#460000
b101101 )
1"
#461000
b101110 %
#465000
0"
#470000
b101110 )
1"
#471000
b101111 %
#475000
0"
#480000
b101111 )
1"
#481000
b110000 %
#485000
0"
#490000
b110000 )
1"
#491000
b110001 %
#495000
0"
#500000
b110001 )
1"
#501000
b110010 %
#505000
0"
#510000
b110010 )
1"
#511000
b110011 %
#515000
0"
#520000
b110011 )
1"
#521000
b110100 %
#525000
0"
#530000
b110100 )
1"
#531000
b110101 %
#535000
0"
#540000
b110101 )
1"
#541000
b110110 %
#545000
0"
#550000
b110110 )
1"
#551000
b110111 %
#555000
0"
#560000
b110111 )
1"
#561000
b111000 %
#565000
0"
#570000
b111000 )
1"
#571000
b111001 %
#575000
0"
#580000
b111001 )
1"
#581000
b111010 %
#585000
0"
#590000
b111010 )
1"
#591000
b111011 %
#595000
0"
#600000
b111011 )
1"
#601000
b111100 %
#605000
0"
#610000
b111100 )
1"
#611000
b111101 %
#615000
0"
#620000
b111101 )
1"
#621000
b111110 %
#625000
0"
#630000
b111110 )
1"
#631000
b111111 %
#635000
0"
#640000
b111111 )
1"
#641000
b1000000 %
#645000
0"
#650000
b1000000 )
1"
#651000
b1000001 %
#655000
0"
#660000
b1000001 )
1"
#661000
b1000010 %
#665000
0"
#670000
b1000010 )
1"
#671000
b1000011 %
#675000
0"
#680000
b1000011 )
1"
#681000
b1000100 %
#685000
0"
#690000
b1000100 )
1"
#691000
b1000101 %
#695000
0"
#700000
b1000101 )
1"
#701000
b1000110 %
#705000
0"
#710000
b1000110 )
1"
#711000
b1000111 %
#715000
0"
#720000
b1000111 )
1"
#721000
b1001000 %
#725000
0"
#730000
b1001000 )
1"
#731000
b1001001 %
#735000
0"
#740000
b1001001 )
1"
#741000
b1001010 %
#745000
0"
#750000
b1001010 )
1"
#751000
b1001011 %
#755000
0"
#760000
b1001011 )
1"
#761000
b1001100 %
#765000
0"
#770000
b1001100 )
1"
#771000
b1001101 %
#775000
0"
#780000
b1001101 )
1"
#781000
b1001110 %
#785000
0"
#790000
b1001110 )
1"
#791000
b1001111 %
#795000
0"
#800000
b1001111 )
1"
#801000
b1010000 %
#805000
0"
#810000
b1010000 )
1"
#811000
b1010001 %
#815000
0"
#820000
b1010001 )
1"
#821000
b1010010 %
#825000
0"
#830000
b1010010 )
1"
#831000
b1010011 %
#835000
0"
#840000
b1010011 )
1"
#841000
b1010100 %
#845000
0"
#850000
b1010100 )
1"
#851000
b1010101 %
#855000
0"
#860000
b1010101 )
1"
#861000
b1010110 %
#865000
0"
#870000
b1010110 )
1"
#871000
b1010111 %
#875000
0"
#880000
b1010111 )
1"
#881000
b1011000 %
#885000
0"
#890000
b1011000 )
1"
#891000
b1011001 %
#895000
0"
#900000
b1011001 )
1"
#901000
b1011010 %
#905000
0"
#910000
b1011010 )
1"
#911000
b1011011 %
#915000
0"
#920000
b1011011 )
1"
#921000
b1011100 %
#925000
0"
#930000
b1011100 )
1"
#931000
b1011101 %
#935000
0"
#940000
b1011101 )
1"
#941000
b1011110 %
#945000
0"
#950000
b1011110 )
1"
#951000
b1011111 %
#955000
0"
#960000
b1011111 )
1"
#961000
b1100000 %
#965000
0"
#970000
b1100000 )
1"
#971000
b1100001 %
#975000
0"
#980000
b1100001 )
1"
#981000
b1100010 %
#985000
0"
#990000
b1100010 )
1"
#991000
b1100011 %
#995000
0"
#1000000
b1100011 )
1"
#1001000
b1100100 %
